[
    {
    "date": "2024-12-11T23:00:00+00:00",
    "tourn_short": "UCL",
    "season": "24-25",
    "tourn_round": "LS-6",
    "home": "Borussia Dortmund",
    "away": "Barcelona",
    "goals": {
        "home": null,
        "away": null
        },
    "NATpos": {
        "home": 6,
        "away": 2
        }
    },
    {
    "date": "2024-12-11T23:00:00+00:00",
    "tourn_short": "UCL",
    "season": "24-25",
    "tourn_round": "LS-6",
    "home": "Juventus",
    "away": "Manchester City",
    "goals": {
        "home": null,
        "away": null
        },
    "NATpos": {
        "home": 6,
        "away": 4
        }
    },
    {
    "date": "2024-12-11T23:00:00+00:00",
    "tourn_short": "UCL",
    "season": "24-25",
    "tourn_round": "LS-6",
    "home": "Arsenal",
    "away": "Monaco",
    "goals": {
        "home": null,
        "away": null
        },
    "NATpos": {
        "home": 3,
        "away": 3
        }
    }
]
